fluentcms_countdown/__init__.py
fluentcms_countdown/appsettings.py
fluentcms_countdown/content_plugins.py
fluentcms_countdown/models.py
fluentcms_countdown/tests.py
fluentcms_countdown/locale/en/LC_MESSAGES/django.mo
fluentcms_countdown/locale/en/LC_MESSAGES/django.po
fluentcms_countdown/locale/nl/LC_MESSAGES/django.mo
fluentcms_countdown/locale/nl/LC_MESSAGES/django.po
fluentcms_countdown/migrations/0001_initial.py
fluentcms_countdown/migrations/__init__.py
fluentcms_countdown/static/fluentcms_countdown/countdown.js
fluentcms_countdown/static/fluentcms_countdown/vendor/jquery.countdown-ar.js
fluentcms_countdown/static/fluentcms_countdown/vendor/jquery.countdown-bg.js
fluentcms_countdown/static/fluentcms_countdown/vendor/jquery.countdown-bn.js
fluentcms_countdown/static/fluentcms_countdown/vendor/jquery.countdown-bs.js
fluentcms_countdown/static/fluentcms_countdown/vendor/jquery.countdown-ca.js
fluentcms_countdown/static/fluentcms_countdown/vendor/jquery.countdown-cs.js
fluentcms_countdown/static/fluentcms_countdown/vendor/jquery.countdown-cy.js
fluentcms_countdown/static/fluentcms_countdown/vendor/jquery.countdown-da.js
fluentcms_countdown/static/fluentcms_countdown/vendor/jquery.countdown-de.js
fluentcms_countdown/static/fluentcms_countdown/vendor/jquery.countdown-el.js
fluentcms_countdown/static/fluentcms_countdown/vendor/jquery.countdown-es.js
fluentcms_countdown/static/fluentcms_countdown/vendor/jquery.countdown-et.js
fluentcms_countdown/static/fluentcms_countdown/vendor/jquery.countdown-fa.js
fluentcms_countdown/static/fluentcms_countdown/vendor/jquery.countdown-fi.js
fluentcms_countdown/static/fluentcms_countdown/vendor/jquery.countdown-fo.js
fluentcms_countdown/static/fluentcms_countdown/vendor/jquery.countdown-fr.js
fluentcms_countdown/static/fluentcms_countdown/vendor/jquery.countdown-gl.js
fluentcms_countdown/static/fluentcms_countdown/vendor/jquery.countdown-gu.js
fluentcms_countdown/static/fluentcms_countdown/vendor/jquery.countdown-he.js
fluentcms_countdown-2.0.dist-info/AUTHORS
fluentcms_countdown-2.0.dist-info/LICENSE
fluentcms_countdown-2.0.dist-info/METADATA
fluentcms_countdown-2.0.dist-info/WHEEL
fluentcms_countdown-2.0.dist-info/top_level.txt
fluentcms_countdown-2.0.dist-info/RECORD
